thekey.py
thekey-2.0.2.dist-info/METADATA
thekey-2.0.2.dist-info/WHEEL
thekey-2.0.2.dist-info/entry_points.txt
thekey-2.0.2.dist-info/top_level.txt
thekey-2.0.2.dist-info/RECORD
