Metadata-Version: 2.1
Name: thekey
Version: 2.0.2
Summary: Help You Find Any Text Queqly!|帮你快速查询文本！
Home-page: UNKNOWN
Author: Python学霸
Author-email: python@xueba.com
License: UNKNOWN
Platform: UNKNOWN
